{
  "search_metadata": {
    "id": "697a362ca3882da506d90364",
    "status": "Success",
    "json_endpoint": "https://serpapi.com/searches/71e0f1e6ef20cf07/697a362ca3882da506d90364.json",
    "created_at": "2026-01-28 16:15:40 UTC",
    "processed_at": "2026-01-28 16:15:40 UTC",
    "google_patents_details_url": "https://patents.google.com/patent/JP2010252671A/en",
    "raw_html_file": "https://serpapi.com/searches/71e0f1e6ef20cf07/697a362ca3882da506d90364.html",
    "total_time_taken": 0.96
  },
  "search_parameters": {
    "engine": "google_patents_details",
    "patent_id": "patent/JP2010252671A/en"
  },
  "title": "Plant light irradiation equipment",
  "type": "patent",
  "pdf": "https://patentimages.storage.googleapis.com/49/0d/f1/9255c65948f86a/JP2010252671A.pdf",
  "publication_number": "JP2010252671A",
  "country": "Japan",
  "prior_art_keywords": [
    "light",
    "light source",
    "plant",
    "bunker",
    "insects"
  ],
  "prior_art_date": "2009-04-23",
  "application_number": "JP2009105315A",
  "inventors": [
    {
      "name": "Masanori Ishiwatari",
      "link": "https://patents.google.com/?inventor=Masanori+Ishiwatari",
      "serpapi_link": "https://serpapi.com/search.json?engine=google_patents&inventor=Masanori+Ishiwatari"
    },
    {
      "name": "\u6b63\u7d00 \u77f3\u6e21",
      "link": "https://patents.google.com/?inventor=%E6%AD%A3%E7%B4%80+%E7%9F%B3%E6%B8%A1",
      "serpapi_link": "https://serpapi.com/search.json?engine=google_patents&inventor=%E6%AD%A3%E7%B4%80+%E7%9F%B3%E6%B8%A1"
    },
    {
      "name": "Makoto Yamada",
      "link": "https://patents.google.com/?inventor=Makoto+Yamada",
      "serpapi_link": "https://serpapi.com/search.json?engine=google_patents&inventor=Makoto+Yamada"
    },
    {
      "name": "\u771f \u5c71\u7530",
      "link": "https://patents.google.com/?inventor=%E7%9C%9F+%E5%B1%B1%E7%94%B0",
      "serpapi_link": "https://serpapi.com/search.json?engine=google_patents&inventor=%E7%9C%9F+%E5%B1%B1%E7%94%B0"
    },
    {
      "name": "Hiroyuki Sekii",
      "link": "https://patents.google.com/?inventor=Hiroyuki+Sekii",
      "serpapi_link": "https://serpapi.com/search.json?engine=google_patents&inventor=Hiroyuki+Sekii"
    },
    {
      "name": "\u5e83\u884c \u95a2\u4e95",
      "link": "https://patents.google.com/?inventor=%E5%BA%83%E8%A1%8C+%E9%96%A2%E4%BA%95",
      "serpapi_link": "https://serpapi.com/search.json?engine=google_patents&inventor=%E5%BA%83%E8%A1%8C+%E9%96%A2%E4%BA%95"
    },
    {
      "name": "Tatsukiyo Uchida",
      "link": "https://patents.google.com/?inventor=Tatsukiyo+Uchida",
      "serpapi_link": "https://serpapi.com/search.json?engine=google_patents&inventor=Tatsukiyo+Uchida"
    },
    {
      "name": "\u9054\u6e05 \u5185\u7530",
      "link": "https://patents.google.com/?inventor=%E9%81%94%E6%B8%85+%E5%86%85%E7%94%B0",
      "serpapi_link": "https://serpapi.com/search.json?engine=google_patents&inventor=%E9%81%94%E6%B8%85+%E5%86%85%E7%94%B0"
    },
    {
      "name": "Yuki Shirakawa",
      "link": "https://patents.google.com/?inventor=Yuki+Shirakawa",
      "serpapi_link": "https://serpapi.com/search.json?engine=google_patents&inventor=Yuki+Shirakawa"
    },
    {
      "name": "\u53cb\u6a39 \u767d\u5ddd",
      "link": "https://patents.google.com/?inventor=%E5%8F%8B%E6%A8%B9+%E7%99%BD%E5%B7%9D",
      "serpapi_link": "https://serpapi.com/search.json?engine=google_patents&inventor=%E5%8F%8B%E6%A8%B9+%E7%99%BD%E5%B7%9D"
    },
    {
      "name": "Hiromichi Shibazaki",
      "link": "https://patents.google.com/?inventor=Hiromichi+Shibazaki",
      "serpapi_link": "https://serpapi.com/search.json?engine=google_patents&inventor=Hiromichi+Shibazaki"
    },
    {
      "name": "\u5f18\u9053 \u67f4\u25b2\u5d0e\u25bc",
      "link": "https://patents.google.com/?inventor=%E5%BC%98%E9%81%93+%E6%9F%B4%E2%96%B2%E5%B4%8E%E2%96%BC",
      "serpapi_link": "https://serpapi.com/search.json?engine=google_patents&inventor=%E5%BC%98%E9%81%93+%E6%9F%B4%E2%96%B2%E5%B4%8E%E2%96%BC"
    }
  ],
  "assignees": [
    "Panasonic Electric Works Co Ltd"
  ],
  "priority_date": "2009-04-23",
  "filing_date": "2009-04-23",
  "publication_date": "2010-11-11",
  "worldwide_applications": {
    "2009": [
      {
        "filing_date": "2009-04-23",
        "country_code": "JP",
        "application_number": "JP2009105315A",
        "document_id": "patent/JP2010252671A/en",
        "legal_status_cat": "not_active",
        "legal_status": "Withdrawn",
        "this_app": true
      }
    ]
  },
  "events": [
    {
      "date": "2009-04-23",
      "title": "Application filed by Panasonic Electric Works Co Ltd",
      "type": "filed",
      "critical": true,
      "assignee_search": "Panasonic Electric Works Co Ltd"
    },
    {
      "date": "2009-04-23",
      "title": "Priority to JP2009105315A",
      "type": "priority",
      "critical": true,
      "document_id": "patent/JP2010252671A/en"
    },
    {
      "date": "2010-11-11",
      "title": "Publication of JP2010252671A",
      "type": "publication",
      "critical": true,
      "document_id": "patent/JP2010252671A/en"
    },
    {
      "date": "Status",
      "title": "Withdrawn",
      "type": "legal-status",
      "critical": true,
      "current": true
    }
  ],
  "external_links": [
    {
      "text": "Espacenet",
      "link": "https://worldwide.espacenet.com/publicationDetails/biblio?CC=JP&NR=2010252671A&KC=A&FT=D"
    },
    {
      "text": "Global Dossier",
      "link": "https://globaldossier.uspto.gov/result/application/JP/2009105315/1"
    },
    {
      "text": "Discuss",
      "link": "https://patents.stackexchange.com/questions/tagged/JP2010252671A"
    }
  ],
  "images": [
    "https://patentimages.storage.googleapis.com/58/8d/46/ee2dc879cb02b7/2010252671-4.png",
    "https://patentimages.storage.googleapis.com/e8/ac/3f/807e15aa944eba/2010252671-5.png",
    "https://patentimages.storage.googleapis.com/45/cb/f8/f05597287185ab/2010252671-6.png"
  ],
  "abstract": "In a plant light irradiation device, natural enemy insects are effectively propagated by a bunker plant so as to increase the density of natural enemy insects in a cultivation field and to surely prevent crop damage caused by pests.  [Solution]  The plant light irradiation apparatus 1 includes a light source 4 that irradiates light to a bunker plant 3 that breeds natural enemy insects of pests in a house farm field 2. The light emitted from the light source 4 has a wavelength peak at 300 to 700 nm. By irradiating light having a wavelength peak from 300 to 700 nm from the light source 4, the bunker plant 3 receives light that promotes plant growth or attracts insects. Thereby, withering of the bunker plant 3 can be prevented, and the prey insect of the natural enemy insect can be fixed to the bunker plant 3, so that the natural enemy insect can effectively breed.  [Selection] Figure 1",
  "abstract_original": "\u3010\u8ab2\u984c\u3011\u690d\u7269\u7528\u5149\u7167\u5c04\u88c5\u7f6e\u306b\u304a\u3044\u3066\u3001\u30d0\u30f3\u30ab\u30fc\u690d\u7269\u306b\u3088\u308a\u5929\u6575\u6606\u866b\u3092\u52b9\u679c\u7684\u306b\u7e41\u6b96\u3055\u305b\u308b\u3053\u3068\u306b\u3088\u308a\u3001\u683d\u57f9\u5703\u5834\u5185\u306b\u304a\u3044\u3066\u5929\u6575\u6606\u866b\u306e\u751f\u606f\u5bc6\u5ea6\u3092\u9ad8\u3081\u3001\u5bb3\u866b\u306b\u3088\u308b\u8fb2\u4f5c\u7269\u306e\u88ab\u5bb3\u3092\u78ba\u5b9f\u306b\u9632\u3050\u3088\u3046\u306b\u3059\u308b\u3002\u3010\u89e3\u6c7a\u624b\u6bb5\u3011  \u690d\u7269\u7528\u5149\u7167\u5c04\u88c5\u7f6e\uff11\u306f\u3001\u30cf\u30a6\u30b9\u5703\u5834\uff12\u306b\u5c45\u308b\u5bb3\u866b\u306e\u5929\u6575\u6606\u866b\u3092\u7e41\u6b96\u3055\u305b\u308b\u30d0\u30f3\u30ab\u30fc\u690d\u7269\uff13\u306b\u5bfe\u3057\u3066\u5149\u7167\u5c04\u3059\u308b\u5149\u6e90\uff14\u3092\u5099\u3048\u3066\u3044\u308b\u3002\u5149\u6e90\uff14\u304b\u3089\u7167\u5c04\u3055\u308c\u308b\u5149\u306f\u3001\uff13\uff10\uff10\u301c\uff17\uff10\uff10\uff4e\uff4d\u306b\u6ce2\u9577\u30d4\u30fc\u30af\u3092\u6709\u3057\u3066\u3044\u308b\u3002\u5149\u6e90\uff14\u304b\u3089\uff13\uff10\uff10\u301c\uff17\uff10\uff10\uff4e\uff4d\u306b\u6ce2\u9577\u30d4\u30fc\u30af\u3092\u6709\u3059\u308b\u5149\u3092\u7167\u5c04\u3059\u308b\u3053\u3068\u306b\u3088\u308a\u3001\u690d\u7269\u80b2\u6210\u3092\u4fc3\u9032\u3059\u308b\u52b9\u679c\u3001\u53c8\u306f\u866b\u3092\u8a98\u5f15\u3059\u308b\u52b9\u679c\u306e\u3042\u308b\u5149\u3092\u30d0\u30f3\u30ab\u30fc\u690d\u7269\uff13\u306b\u53d7\u5149\u3055\u305b\u308b\u3002\u3053\u308c\u306b\u3088\u308a\u3001\u30d0\u30f3\u30ab\u30fc\u690d\u7269\uff13\u306e\u67af\u308c\u3092\u9632\u6b62\u3057\u305f\u308a\u3001\u5929\u6575\u6606\u866b\u306e\u990c\u6606\u866b\u3092\u30d0\u30f3\u30ab\u30fc\u690d\u7269\uff13\u306b\u5b9a\u7740\u3055\u305b\u308b\u3053\u3068\u304c\u3067\u304d\u3001\u5929\u6575\u6606\u866b\u304c\u52b9\u679c\u7684\u306b\u7e41\u6b96\u3059\u308b\u3088\u3046\u306b\u306a\u308b\u3002\u3010\u9078\u629e\u56f3\u3011\u56f3\uff11",
  "description_link": "https://serpapi.com/searches/697a362ca3882da506d90364/google_patents_details/description.html",
  "claims": [
    "\u683d\u57f9\u5703\u5834\u306b\u5c45\u308b\u5bb3\u866b\u306e\u5929\u6575\u6606\u866b\u3092\u7e41\u6b96\u3055\u305b\u308b\u30d0\u30f3\u30ab\u30fc\u690d\u7269\u306b\u5bfe\u3057\u3066\u5149\u7167\u5c04\u3059\u308b\u5149\u6e90\u3092\u6709\u3057\u305f\u690d\u7269\u7528\u5149\u7167\u5c04\u88c5\u7f6e\u3067\u3042\u3063\u3066\u3001\n  \u524d\u8a18\u5149\u6e90\u304b\u3089\u7167\u5c04\u3055\u308c\u308b\u5149\u306f\u3001\uff13\uff10\uff10\u301c\uff17\uff10\uff10\uff4e\uff4d\u306b\u6ce2\u9577\u30d4\u30fc\u30af\u3092\u6709\u3059\u308b\u3053\u3068\u3092\u7279\u5fb4\u3068\u3059\u308b\u690d\u7269\u7528\u5149\u7167\u5c04\u88c5\u7f6e\u3002\nA plant light irradiation device having a light source for irradiating light to a bunker plant that breeds natural enemy insects of pests in a cultivation field,  The light irradiated from the light source has a wavelength peak at 300 to 700 nm.",
    "\u524d\u8a18\u5149\u6e90\u304b\u3089\u7167\u5c04\u3055\u308c\u308b\u5149\u306f\u3001\uff13\uff10\uff10\u301c\uff14\uff10\uff10\uff4e\uff4d\u306b\u6ce2\u9577\u30d4\u30fc\u30af\u3092\u6709\u3059\u308b\u3053\u3068\u3092\u7279\u5fb4\u3068\u3059\u308b\u8acb\u6c42\u9805\uff11\u306b\u8a18\u8f09\u306e\u690d\u7269\u7528\u5149\u7167\u5c04\u88c5\u7f6e\u3002\n\n\u00a0\u00a0The light irradiation apparatus for plants according to claim 1, wherein the light emitted from the light source has a wavelength peak at 300 to 400 nm.",
    "\u524d\u8a18\u5149\u6e90\u304b\u3089\u7167\u5c04\u3055\u308c\u308b\u5149\u306f\u3001\uff16\uff10\uff10\u301c\uff17\uff10\uff10\uff4e\uff4d\u306b\u6ce2\u9577\u30d4\u30fc\u30af\u3092\u6709\u3059\u308b\u3053\u3068\u3092\u7279\u5fb4\u3068\u3059\u308b\u8acb\u6c42\u9805\uff11\u306b\u8a18\u8f09\u306e\u690d\u7269\u7528\u5149\u7167\u5c04\u88c5\u7f6e\u3002\n\n\u00a0\u00a0The light irradiation apparatus for plants according to claim 1, wherein the light emitted from the light source has a wavelength peak at 600 to 700 nm.",
    "\u5929\u5019\u72b6\u614b\u53c8\u306f\u30d0\u30f3\u30ab\u30fc\u690d\u7269\u306b\u7740\u751f\u3059\u308b\u5929\u6575\u6606\u866b\u306e\u990c\u6606\u866b\u306e\u7e41\u6b96\u6642\u671f\u3092\u691c\u77e5\u3059\u308b\u691c\u77e5\u90e8\u3068\u3001\n  \u524d\u8a18\u691c\u77e5\u90e8\u306b\u3088\u308b\u691c\u77e5\u7d50\u679c\u306b\u57fa\u3065\u304d\u524d\u8a18\u5149\u6e90\u3092\u70b9\u706f\u5236\u5fa1\u3059\u308b\u5236\u5fa1\u90e8\u3068\u3092\u5099\u3048\u3001\n  \u524d\u8a18\u5236\u5fa1\u90e8\u306f\u3001\n  \u524d\u8a18\u691c\u77e5\u90e8\u306b\u3088\u308a\u30d0\u30f3\u30ab\u30fc\u690d\u7269\u304c\u767a\u80b2\u3057\u306a\u3044\u5929\u5019\u304c\u7d99\u7d9a\u3057\u3066\u3044\u308b\u3068\u5224\u65ad\u3055\u308c\u308b\u3068\u304d\u3001\u53c8\u306f\u990c\u6606\u866b\u306e\u7e41\u6b96\u6642\u671f\u306b\u3042\u308b\u3068\u5224\u65ad\u3055\u308c\u308b\u3068\u304d\u3001\u524d\u8a18\u5149\u6e90\u3092\u70b9\u706f\u3055\u305b\u3001\n  \u4e0a\u8a18\u4ee5\u5916\u3068\u5224\u65ad\u3055\u308c\u308b\u3068\u304d\u3001\u524d\u8a18\u5149\u6e90\u3092\u6d88\u706f\u3001\u53c8\u306f\u524d\u8a18\u5149\u6e90\u306e\u5149\u51fa\u529b\u3092\u4f4e\u4e0b\u3055\u305b\u308b\u3053\u3068\u3092\u7279\u5fb4\u3059\u308b\u8acb\u6c42\u9805\uff11\u4e43\u81f3\u8acb\u6c42\u9805\uff13\u306e\u3044\u305a\u308c\u304b\u4e00\u9805\u306b\u8a18\u8f09\u306e\u690d\u7269\u7528\u5149\u7167\u5c04\u88c5\u7f6e\u3002\nA detection unit that detects the breeding time of the prey insects of the natural enemy insects growing on the weather condition or bunker plants,  A control unit that controls lighting of the light source based on a detection result by the detection unit,  The controller is  When it is determined by the detection unit that the bunker plant does not grow, or when it is determined that it is in the breeding season of prey insects, the light source is turned on,  4. The plant light irradiation device according to claim 1, wherein when it is determined to be other than the above, the light source is turned off or the light output of the light source is reduced.",
    "\u524d\u8a18\u5149\u6e90\u306b\u306f\u3001\u305d\u306e\u5149\u7167\u5c04\u4f4d\u7f6e\u304c\u53ef\u5909\u81ea\u5728\u3068\u306a\u308b\u3088\u3046\u306b\u8a72\u5149\u6e90\u3092\u4fdd\u6301\u3059\u308b\u53ef\u5909\u4fdd\u6301\u69cb\u9020\u304c\u8a2d\u3051\u3089\u308c\u3066\u304a\u308a\u3001\n  \u524d\u8a18\u5149\u6e90\u306e\u5149\u7167\u5c04\u4f4d\u7f6e\u306f\u3001\u30d0\u30f3\u30ab\u30fc\u690d\u7269\u306e\u751f\u9577\u70b9\u306b\u8a2d\u5b9a\u3055\u308c\u308b\u3053\u3068\u3092\u7279\u5fb4\u3068\u3059\u308b\u8acb\u6c42\u9805\uff11\u4e43\u81f3\u8acb\u6c42\u9805\uff14\u306e\u3044\u305a\u308c\u304b\u4e00\u9805\u306b\u8a18\u8f09\u306e\u690d\u7269\u7528\u5149\u7167\u5c04\u88c5\u7f6e\u3002\nThe light source is provided with a variable holding structure for holding the light source so that the light irradiation position is variable.  The light irradiation position of the said light source is set to the growth point of a bunker plant, The light irradiation apparatus for plants as described in any one of Claim 1 thru | or 4 characterized by the above-mentioned."
  ],
  "priority_applications": [
    {
      "application_number": "JP2009105315A",
      "representative_publication": "JP2010252671A",
      "primary_language": "en",
      "priority_date": "2009-04-23",
      "filing_date": "2009-04-23",
      "title": "Plant light irradiation equipment"
    }
  ],
  "applications_claiming_priority": [
    {
      "application_number": "JP2009105315A",
      "representative_publication": "JP2010252671A",
      "primary_language": "en",
      "priority_date": "2009-04-23",
      "filing_date": "2009-04-23",
      "title": "Plant light irradiation equipment"
    }
  ],
  "family_id": "43314345",
  "cited_by": {
    "original": [
      {
        "publication_number": "JP2012024058A",
        "primary_language": "en",
        "examiner_cited": "*",
        "priority_date": "2010-07-27",
        "publication_date": "2012-02-09",
        "assignee_original": "Panasonic Electric Works Co Ltd",
        "title": "Lighting method and lighting system for insect pest attraction",
        "patent_id": "patent/JP2012024058A/en",
        "serpapi_link": "https://serpapi.com/search.json?engine=google_patents_details&patent_id=patent%2FJP2012024058A%2Fen"
      },
      {
        "publication_number": "US20120176765A1",
        "primary_language": "en",
        "examiner_cited": "*",
        "priority_date": "2009-08-26",
        "publication_date": "2012-07-12",
        "assignee_original": "Panasonic Corporation",
        "title": "Insect attractant lighting method and insect attractant lighting system",
        "patent_id": "patent/US20120176765A1/en",
        "serpapi_link": "https://serpapi.com/search.json?engine=google_patents_details&patent_id=patent%2FUS20120176765A1%2Fen"
      },
      {
        "publication_number": "WO2015079767A1",
        "primary_language": "en",
        "examiner_cited": "*",
        "priority_date": "2013-11-29",
        "publication_date": "2015-06-04",
        "assignee_original": "\u96c5\u654f \u5800",
        "title": "Pest control method and control device",
        "patent_id": "patent/WO2015079767A1/en",
        "serpapi_link": "https://serpapi.com/search.json?engine=google_patents_details&patent_id=patent%2FWO2015079767A1%2Fen"
      },
      {
        "publication_number": "JP2016002027A",
        "primary_language": "en",
        "examiner_cited": "*",
        "priority_date": "2014-06-16",
        "publication_date": "2016-01-12",
        "assignee_original": "\u30b7\u30e3\u30fc\u30d7\u682a\u5f0f\u4f1a\u793e",
        "title": "Illumination method, illumination device and insect plant cultivation facility",
        "patent_id": "patent/JP2016002027A/en",
        "serpapi_link": "https://serpapi.com/search.json?engine=google_patents_details&patent_id=patent%2FJP2016002027A%2Fen"
      },
      {
        "publication_number": "JP2016146792A",
        "primary_language": "en",
        "examiner_cited": "*",
        "priority_date": "2015-02-13",
        "publication_date": "2016-08-18",
        "assignee_original": "\u682a\u5f0f\u4f1a\u793e\u30a2\u30b0\u30ea\u7dcf\u7814",
        "title": "Manufacturing method of bunker type biological pesticide",
        "patent_id": "patent/JP2016146792A/en",
        "serpapi_link": "https://serpapi.com/search.json?engine=google_patents_details&patent_id=patent%2FJP2016146792A%2Fen"
      },
      {
        "publication_number": "JP2016208944A",
        "primary_language": "en",
        "examiner_cited": "*",
        "priority_date": "2015-05-13",
        "publication_date": "2016-12-15",
        "assignee_original": "\u6469\u8036 \u8352\u91d1",
        "title": "Insect lamp",
        "patent_id": "patent/JP2016208944A/en",
        "serpapi_link": "https://serpapi.com/search.json?engine=google_patents_details&patent_id=patent%2FJP2016208944A%2Fen"
      },
      {
        "publication_number": "JP2019061706A",
        "primary_language": "en",
        "examiner_cited": "*",
        "priority_date": "2018-11-30",
        "publication_date": "2019-04-18",
        "assignee_original": "\u30a2\u30b7\u30b9\u30c8\u30b7\u30b9\u30c6\u30e0\u30ba\u682a\u5f0f\u4f1a\u793e",
        "title": "Server device, database system, and search program",
        "patent_id": "patent/JP2019061706A/en",
        "serpapi_link": "https://serpapi.com/search.json?engine=google_patents_details&patent_id=patent%2FJP2019061706A%2Fen"
      },
      {
        "publication_number": "US11517007B2",
        "primary_language": "en",
        "priority_date": "2016-08-18",
        "publication_date": "2022-12-06",
        "assignee_original": "Panasonic Intellectual Property Management Co., Ltd.",
        "title": "Pest control apparatus",
        "patent_id": "patent/US11517007B2/en",
        "serpapi_link": "https://serpapi.com/search.json?engine=google_patents_details&patent_id=patent%2FUS11517007B2%2Fen"
      }
    ]
  },
  "similar_documents": [
    {
      "is_patent": true,
      "publication_number": "JP2010252671A",
      "primary_language": "en",
      "publication_date": "2010-11-11",
      "title": "Plant light irradiation equipment",
      "patent_id": "patent/JP2010252671A/en",
      "serpapi_link": "https://serpapi.com/search.json?engine=google_patents_details&patent_id=patent%2FJP2010252671A%2Fen"
    },
    {
      "is_patent": true,
      "publication_number": "CN102573454B",
      "primary_language": "en",
      "publication_date": "2013-09-18",
      "title": "Insect attractant lighting method and insect attractant lighting system",
      "patent_id": "patent/CN102573454B/en",
      "serpapi_link": "https://serpapi.com/search.json?engine=google_patents_details&patent_id=patent%2FCN102573454B%2Fen"
    },
    {
      "is_patent": true,
      "publication_number": "EP2338326B1",
      "primary_language": "en",
      "publication_date": "2016-11-30",
      "title": "Lighting system for preventing plant disease damage",
      "patent_id": "patent/EP2338326B1/en",
      "serpapi_link": "https://serpapi.com/search.json?engine=google_patents_details&patent_id=patent%2FEP2338326B1%2Fen"
    },
    {
      "is_patent": true,
      "publication_number": "CN114097762B",
      "primary_language": "en",
      "publication_date": "2024-02-09",
      "title": "egg trap",
      "patent_id": "patent/CN114097762B/en",
      "serpapi_link": "https://serpapi.com/search.json?engine=google_patents_details&patent_id=patent%2FCN114097762B%2Fen"
    },
    {
      "is_patent": true,
      "publication_number": "US20170094960A1",
      "primary_language": "en",
      "publication_date": "2017-04-06",
      "title": "Insect control device and method of using the same",
      "patent_id": "patent/US20170094960A1/en",
      "serpapi_link": "https://serpapi.com/search.json?engine=google_patents_details&patent_id=patent%2FUS20170094960A1%2Fen"
    },
    {
      "is_patent": true,
      "publication_number": "KR100795435B1",
      "primary_language": "en",
      "publication_date": "2008-01-17",
      "title": "Pest Removal Device",
      "patent_id": "patent/KR100795435B1/en",
      "serpapi_link": "https://serpapi.com/search.json?engine=google_patents_details&patent_id=patent%2FKR100795435B1%2Fen"
    },
    {
      "is_patent": true,
      "publication_number": "US20190000061A1",
      "primary_language": "en",
      "publication_date": "2019-01-03",
      "title": "Method for attracting or fixing predatory insects",
      "patent_id": "patent/US20190000061A1/en",
      "serpapi_link": "https://serpapi.com/search.json?engine=google_patents_details&patent_id=patent%2FUS20190000061A1%2Fen"
    },
    {
      "is_patent": true,
      "publication_number": "JP6555466B2",
      "primary_language": "en",
      "publication_date": "2019-08-07",
      "title": "Insect control method by flashing illumination and lighting device for insect control",
      "patent_id": "patent/JP6555466B2/en",
      "serpapi_link": "https://serpapi.com/search.json?engine=google_patents_details&patent_id=patent%2FJP6555466B2%2Fen"
    },
    {
      "is_patent": true,
      "publication_number": "JP2005229997A5",
      "primary_language": "en",
      "publication_date": "2005-10-27",
      "patent_id": "patent/JP2005229997A5/en",
      "serpapi_link": "https://serpapi.com/search.json?engine=google_patents_details&patent_id=patent%2FJP2005229997A5%2Fen"
    },
    {
      "is_patent": true,
      "publication_number": "JP2009261289A",
      "primary_language": "en",
      "publication_date": "2009-11-12",
      "title": "Lighting device for plant disease prevention",
      "patent_id": "patent/JP2009261289A/en",
      "serpapi_link": "https://serpapi.com/search.json?engine=google_patents_details&patent_id=patent%2FJP2009261289A%2Fen"
    },
    {
      "is_scholar": true,
      "scholar_id": "18103001101838758399",
      "scholar_authors": "Johansen et al.",
      "publication_date": "2018",
      "title": "Phototactic response of Frankliniella occidentalis to sticky traps with blue light emitting diodes in herb and Alstroemeria greenhouses",
      "patent_id": "scholar/18103001101838758399",
      "serpapi_link": "https://serpapi.com/search.json?engine=google_patents_details&patent_id=scholar%2F18103001101838758399"
    },
    {
      "is_patent": true,
      "publication_number": "CN107969399B",
      "primary_language": "en",
      "publication_date": "2020-06-19",
      "title": "Insect trapping lamp tube with multiple single wave bands and control method thereof",
      "patent_id": "patent/CN107969399B/en",
      "serpapi_link": "https://serpapi.com/search.json?engine=google_patents_details&patent_id=patent%2FCN107969399B%2Fen"
    },
    {
      "is_scholar": true,
      "scholar_id": "7804610534949626176",
      "scholar_authors": "Styrsky et al.",
      "publication_date": "2004",
      "title": "Endogenous control of migration and calendar effects in an intratropical migrant, the yellow-green vireo",
      "patent_id": "scholar/7804610534949626176",
      "serpapi_link": "https://serpapi.com/search.json?engine=google_patents_details&patent_id=scholar%2F7804610534949626176"
    },
    {
      "is_patent": true,
      "publication_number": "JP4389557B2",
      "primary_language": "en",
      "publication_date": "2009-12-24",
      "title": "Insect control equipment",
      "patent_id": "patent/JP4389557B2/en",
      "serpapi_link": "https://serpapi.com/search.json?engine=google_patents_details&patent_id=patent%2FJP4389557B2%2Fen"
    },
    {
      "is_patent": true,
      "publication_number": "US20210400945A1",
      "primary_language": "en",
      "publication_date": "2021-12-30",
      "title": "Arthropod trap and extermination method",
      "patent_id": "patent/US20210400945A1/en",
      "serpapi_link": "https://serpapi.com/search.json?engine=google_patents_details&patent_id=patent%2FUS20210400945A1%2Fen"
    },
    {
      "is_patent": true,
      "publication_number": "JP3879557B2",
      "primary_language": "en",
      "publication_date": "2007-02-14",
      "title": "Protective lighting method and apparatus",
      "patent_id": "patent/JP3879557B2/en",
      "serpapi_link": "https://serpapi.com/search.json?engine=google_patents_details&patent_id=patent%2FJP3879557B2%2Fen"
    },
    {
      "is_patent": true,
      "publication_number": "JP6540944B2",
      "primary_language": "en",
      "publication_date": "2019-07-10",
      "title": "Pest control method of plant body",
      "patent_id": "patent/JP6540944B2/en",
      "serpapi_link": "https://serpapi.com/search.json?engine=google_patents_details&patent_id=patent%2FJP6540944B2%2Fen"
    },
    {
      "is_patent": true,
      "publication_number": "KR100960299B1",
      "primary_language": "en",
      "publication_date": "2010-06-07",
      "title": "Farmland Pest Control Using Frogs",
      "patent_id": "patent/KR100960299B1/en",
      "serpapi_link": "https://serpapi.com/search.json?engine=google_patents_details&patent_id=patent%2FKR100960299B1%2Fen"
    },
    {
      "is_scholar": true,
      "scholar_id": "3014026897255979407",
      "scholar_authors": "Jachowski et al.",
      "publication_date": "2005",
      "title": "Introducing an innovative semi\u2010captive environment for the Philippine tarsier (Tarsius syrichta)",
      "patent_id": "scholar/3014026897255979407",
      "serpapi_link": "https://serpapi.com/search.json?engine=google_patents_details&patent_id=scholar%2F3014026897255979407"
    },
    {
      "is_patent": true,
      "publication_number": "JP5114445B2",
      "primary_language": "en",
      "publication_date": "2013-01-09",
      "title": "Insect attracting system",
      "patent_id": "patent/JP5114445B2/en",
      "serpapi_link": "https://serpapi.com/search.json?engine=google_patents_details&patent_id=patent%2FJP5114445B2%2Fen"
    },
    {
      "is_patent": true,
      "publication_number": "JP2010136650A",
      "primary_language": "en",
      "publication_date": "2010-06-24",
      "title": "Method for controlling insect pest and method for growing crop",
      "patent_id": "patent/JP2010136650A/en",
      "serpapi_link": "https://serpapi.com/search.json?engine=google_patents_details&patent_id=patent%2FJP2010136650A%2Fen"
    },
    {
      "is_scholar": true,
      "scholar_id": "6076539235595846326",
      "scholar_authors": "De Vosjoli",
      "publication_date": "2007",
      "title": "The lizard keeper's handbook",
      "patent_id": "scholar/6076539235595846326",
      "serpapi_link": "https://serpapi.com/search.json?engine=google_patents_details&patent_id=scholar%2F6076539235595846326"
    },
    {
      "is_scholar": true,
      "scholar_id": "17955352880606533799",
      "scholar_authors": "Shimoda",
      "publication_date": "2018",
      "title": "Recent advances in the optical control of insect pests using light and color",
      "patent_id": "scholar/17955352880606533799",
      "serpapi_link": "https://serpapi.com/search.json?engine=google_patents_details&patent_id=scholar%2F17955352880606533799"
    },
    {
      "is_patent": true,
      "publication_number": "JP2007111005A",
      "primary_language": "en",
      "publication_date": "2007-05-10",
      "title": "Method and system for controlling insect pest",
      "patent_id": "patent/JP2007111005A/en",
      "serpapi_link": "https://serpapi.com/search.json?engine=google_patents_details&patent_id=patent%2FJP2007111005A%2Fen"
    },
    {
      "is_patent": true,
      "publication_number": "JP2020010637A",
      "primary_language": "en",
      "publication_date": "2020-01-23",
      "title": "How to locally attract or settle natural enemies",
      "patent_id": "patent/JP2020010637A/en",
      "serpapi_link": "https://serpapi.com/search.json?engine=google_patents_details&patent_id=patent%2FJP2020010637A%2Fen"
    }
  ],
  "legal_events": [
    {
      "date": "2012-01-18",
      "code": "A711",
      "title": "Notification of change in applicant",
      "attributes": [
        {
          "label": "Free format text",
          "value": "JAPANESE INTERMEDIATE CODE: A712"
        },
        {
          "label": "Effective date",
          "value": "20120117"
        }
      ]
    },
    {
      "date": "2012-07-03",
      "code": "A300",
      "title": "Withdrawal of application because of no request for examination",
      "attributes": [
        {
          "label": "Free format text",
          "value": "JAPANESE INTERMEDIATE CODE: A300"
        },
        {
          "label": "Effective date",
          "value": "20120703"
        }
      ]
    }
  ]
}